Metadata-Version: 2.1
Name: kumex-python
Version: 2.0.0
Summary: kumex-api-sdk
Home-page: https://github.com/Kucoin/kumex-python-sdk
Author: Grape
Author-email: grape.zhang@kucoin.com
License: MIT
Platform: UNKNOWN
Classifier: Programming Language :: Python :: 3
Classifier: License :: OSI Approved :: MIT License
Classifier: Operating System :: OS Independent
Requires-Dist: requests
Requires-Dist: websockets
